pymineos_.cpython-313-x86_64-linux-gnu.so
pymineos/COPYING
pymineos/__init__.py
pymineos/mineos.py
pymineos/planet_parameters.ini
pymineos-1.2.3.data/scripts/mineos
pymineos-1.2.3.dist-info/licenses/COPYING
pymineos-1.2.3.dist-info/METADATA
pymineos-1.2.3.dist-info/WHEEL
pymineos-1.2.3.dist-info/top_level.txt
pymineos-1.2.3.dist-info/RECORD
